{"type": "FeatureCollection", "features": [{"type": "Feature", "properties": {"filename": "imagen_4.jpeg", "camera": "v2   1200 1600 brown 0.85", "focal": 0.7236923090694978, "width": 1200, "height": 1600, "capture_time": 0.0, "translation": [668195.5047414189, -5.175548892337218, 18.91348438769442], "rotation": [1.8514398636414962, 1.835925978741531, 0.5087983360832466]}, "geometry": {"type": "Point", "coordinates": [-85.48864594157973, -4.6808415064069164e-05, 18.91348438769442]}}, {"type": "Feature", "properties": {"filename": "imagen_1.jpeg", "camera": "v2   1200 1600 brown 0.85", "focal": 0.7236923090694978, "width": 1200, "height": 1600, "capture_time": 0.0, "translation": [668195.8128371857, -10.47028676903815, 14.015843307532466], "rotation": [1.6971595220586615, -1.6509215123170193, -0.8744901546294174]}, "geometry": {"type": "Point", "coordinates": [-85.488643173769, -9.469479247345589e-05, 14.015843307532466]}}, {"type": "Feature", "properties": {"filename": "imagen_2.jpeg", "camera": "v2   1600 1200 brown 0.85", "focal": 0.7201038674862684, "width": 1600, "height": 1200, "capture_time": 0.0, "translation": [668181.4855635479, -2.0953526463495358, 17.720266928934738], "rotation": [2.5549819498584077, -0.08558455994477114, 0.6120434421100406]}, "geometry": {"type": "Point", "coordinates": [-85.4887718842721, -1.8950674439087108e-05, 17.720266928934738]}}, {"type": "Feature", "properties": {"filename": "imagen_5.jpeg", "camera": "v2   1200 1600 brown 0.85", "focal": 0.7236923090694978, "width": 1200, "height": 1600, "capture_time": 0.0, "translation": [668200.7320150053, -4.360725568378145, 17.676716217803598], "rotation": [1.7642349214172726, 1.7856703438965356, 0.2828308952380191]}, "geometry": {"type": "Point", "coordinates": [-85.48859898184467, -3.9439033846930006e-05, 17.676716217803598]}}, {"type": "Feature", "properties": {"filename": "imagen_7.jpeg", "camera": "v2   1600 1200 brown 0.85", "focal": 0.7201038674862684, "width": 1600, "height": 1200, "capture_time": 0.0, "translation": [668193.6514638626, 0.6843528790990305, 21.454548650720707], "rotation": [2.5865034416728814, -0.01693515217213149, 0.08669062344154789]}, "geometry": {"type": "Point", "coordinates": [-85.48866259068481, 6.189386773996955e-06, 21.454548650720707]}}, {"type": "Feature", "properties": {"filename": "imagen_6.jpeg", "camera": "v2   1200 1600 brown 0.85", "focal": 0.7236923090694978, "width": 1200, "height": 1600, "capture_time": 0.0, "translation": [668194.1920600779, 0.698893565317217, 22.050517490551997], "rotation": [1.969434922814675, -2.0184074945384616, -0.32872934246004437]}, "geometry": {"type": "Point", "coordinates": [-85.48865773418453, 6.320894836537829e-06, 22.050517490551997]}}, {"type": "Feature", "properties": {"filename": "imagen_8.jpeg", "camera": "v2   1600 1200 brown 0.85", "focal": 0.7201038674862684, "width": 1600, "height": 1200, "capture_time": 0.0, "translation": [668193.9292189076, -5.337161410535959, 17.577742558028625], "rotation": [2.5527607713480656, -0.017977421126448297, 0.016593819473288477]}, "geometry": {"type": "Point", "coordinates": [-85.488660095444, -4.8270062442544784e-05, 17.577742558028625]}}, {"type": "Feature", "properties": {"filename": "imagen_3.jpeg", "camera": "v2   1200 1600 brown 0.85", "focal": 0.7236923090694978, "width": 1200, "height": 1600, "capture_time": 0.0, "translation": [668184.8557793315, -4.294590422094807, 14.983944688419028], "rotation": [1.5828452468418115, -1.7870229171495493, -0.2377841936326634]}, "geometry": {"type": "Point", "coordinates": [-85.4887416075993, -3.884090057006456e-05, 14.983944688419028]}}, {"type": "Feature", "properties": {"filename": "imagen_11.jpeg", "camera": "v2   1600 1200 brown 0.85", "focal": 0.7201038674862684, "width": 1600, "height": 1200, "capture_time": 0.0, "translation": [668195.5947915879, 6.056026427206658, 21.2323889904985], "rotation": [3.04349465727813, 0.002837183358166652, -0.07907837975480474]}, "geometry": {"type": "Point", "coordinates": [-85.48864513260484, 5.477158161080271e-05, 21.2323889904985]}}, {"type": "Feature", "properties": {"filename": "imagen_10.jpeg", "camera": "v2   1600 1200 brown 0.85", "focal": 0.7201038674862684, "width": 1600, "height": 1200, "capture_time": 0.0, "translation": [668207.27067301, -4.974636883833131, 14.444655762585874], "rotation": [2.4399845800078723, 0.13376295902458896, -0.4335066175698124]}, "geometry": {"type": "Point", "coordinates": [-85.4885402411577, -4.499133550557228e-05, 14.444655762585874]}}, {"type": "Feature", "properties": {"filename": "imagen_9.jpeg", "camera": "v2   1600 1200 brown 0.85", "focal": 0.7201038674862684, "width": 1600, "height": 1200, "capture_time": 0.0, "translation": [668195.8863231243, -11.284976675618019, 11.403662502583863], "rotation": [2.1367212903888646, -0.051386307019461064, -0.02763983322484392]}, "geometry": {"type": "Point", "coordinates": [-85.4886425136004, -0.0001020629661451526, 11.403662502583863]}}]}