{"type": "FeatureCollection", "features": [{"type": "Feature", "properties": {"filename": "4.jpeg", "camera": "v2   1200 1600 brown 0.85", "focal": 0.6968248488198009, "width": 1200, "height": 1600, "capture_time": 0.0, "translation": [-0.1481966030337298, 0.3910860869771951, 0.6383997701958656], "rotation": [-1.7877368192696201, 2.045776123933282, -1.1060049142700161]}, "geometry": {"type": "Point", "coordinates": [-7.488862767299398, 0.0003414609634669522, 0.6383997701958656]}}, {"type": "Feature", "properties": {"filename": "5.jpeg", "camera": "v2   1200 1600 brown 0.85", "focal": 0.6968248488198009, "width": 1200, "height": 1600, "capture_time": 0.0, "translation": [-0.681854582870117, 0.18587907916035862, 0.3708057638203633], "rotation": [1.4245886538511319, -1.9700157786185897, 1.0731944840290926]}, "geometry": {"type": "Point", "coordinates": [-7.489340871007602, 0.00015637697845629375, 0.3708057638203633]}}, {"type": "Feature", "properties": {"filename": "8.jpeg", "camera": "v2   1200 1600 brown 0.85", "focal": 0.6968248488198009, "width": 1200, "height": 1600, "capture_time": 0.0, "translation": [-0.5058597232930172, -0.029384430735303585, 0.7090448029066304], "rotation": [1.7057676676678644, -1.9799340788671422, 0.8502739799391957]}, "geometry": {"type": "Point", "coordinates": [-7.489183197368363, -3.777711924195649e-05, 0.7090448029066304]}}, {"type": "Feature", "properties": {"filename": "3.jpeg", "camera": "v2   1200 1600 brown 0.85", "focal": 0.6968248488198009, "width": 1200, "height": 1600, "capture_time": 0.0, "translation": [0.2504987300692689, 0.2998216529126107, 0.8162836406992443], "rotation": [-2.163368124082443, -1.65568117680391, 0.45734834171803335]}, "geometry": {"type": "Point", "coordinates": [-7.488505576219751, 0.0002591462817666122, 0.8162836406992443]}}, {"type": "Feature", "properties": {"filename": "7.jpeg", "camera": "v2   1200 1600 brown 0.85", "focal": 0.6968248488198009, "width": 1200, "height": 1600, "capture_time": 0.0, "translation": [-0.22263841129996884, 0.23757208911109617, 0.7668767902791473], "rotation": [-1.981712129403802, 2.2179770594566772, -0.9666853915776956]}, "geometry": {"type": "Point", "coordinates": [-7.488929459625405, 0.0002030009236218957, 0.7668767902791473]}}, {"type": "Feature", "properties": {"filename": "11.jpeg", "camera": "v2   1200 1600 brown 0.85", "focal": 0.6968248488198009, "width": 1200, "height": 1600, "capture_time": 0.0, "translation": [-0.3489232301195786, 0.03784089547890379, 1.101700570448288], "rotation": [-2.0221316998086327, -1.8329832724217914, -0.26737496793319465]}, "geometry": {"type": "Point", "coordinates": [-7.489042598087183, 2.2855896548727884e-05, 1.101700570448288]}}, {"type": "Feature", "properties": {"filename": "1.jpeg", "camera": "v2   1200 1600 brown 0.85", "focal": 0.6968248488198009, "width": 1200, "height": 1600, "capture_time": 0.0, "translation": [-0.39123714565242695, 0.40989106689781124, 0.5070138023713631], "rotation": [-1.7114247672851408, -1.5001000278951757, 0.1193885158922796]}, "geometry": {"type": "Point", "coordinates": [-7.489080507180524, 0.00035842177112344466, 0.5070138023713631]}}, {"type": "Feature", "properties": {"filename": "6.jpeg", "camera": "v2   1200 1600 brown 0.85", "focal": 0.6968248488198009, "width": 1200, "height": 1600, "capture_time": 0.0, "translation": [0.3467204079440146, 0.1329942849565652, 0.9193704608839858], "rotation": [-2.206915749676041, -2.0202252621474126, 0.3016973445360517]}, "geometry": {"type": "Point", "coordinates": [-7.488419371179359, 0.00010867837253841711, 0.9193704608839858]}}, {"type": "Feature", "properties": {"filename": "2.jpeg", "camera": "v2   1200 1600 brown 0.85", "focal": 0.6968248488198009, "width": 1200, "height": 1600, "capture_time": 0.0, "translation": [0.16470473534116684, -0.1869551755878933, 1.0349395122990128], "rotation": [2.2038184117656194, 2.2388876315759596, 1.3472188268577226e-05]}, "geometry": {"type": "Point", "coordinates": [-7.488582439028662, -0.0001798961586382444, 1.0349395122990128]}}, {"type": "Feature", "properties": {"filename": "9.jpeg", "camera": "v2   1200 1600 brown 0.85", "focal": 0.6968248488198009, "width": 1200, "height": 1600, "capture_time": 0.0, "translation": [0.25505723916824213, -0.06155594012215751, 1.0598666725272794], "rotation": [-2.256718708138387, -2.024963471065461, 0.10897542516113311]}, "geometry": {"type": "Point", "coordinates": [-7.488501492208947, -6.679385782086287e-05, 1.0598666725272794]}}, {"type": "Feature", "properties": {"filename": "10.jpeg", "camera": "v2   1200 1600 brown 0.85", "focal": 0.6968248488198009, "width": 1200, "height": 1600, "capture_time": 0.0, "translation": [0.04341876621555546, -0.024270048800495853, 1.100178184994122], "rotation": [-2.1762392951532727, -1.9447681046623961, -0.031240034555683152]}, "geometry": {"type": "Point", "coordinates": [-7.488691099082923, -3.316429128089396e-05, 1.100178184994122]}}]}